.flake8
.travis.yml
CHANGELOG.rst
LICENSE.txt
MANIFEST.in
README.rst
pytest.ini
setup.py
test.bash
test_requirements.txt
docs/ExpCM.rst
docs/Makefile
docs/README.rst
docs/acknowledgments.rst
docs/auxiliary_progs.rst
docs/conf.py
docs/howtouse.rst
docs/implementation.rst
docs/index.rst
docs/indices_and_tables.rst
docs/installation.rst
docs/phydms_comprehensive_prog.rst
docs/phydms_logoplot.rst
docs/phydms_prepalignment.rst
docs/phydms_prog.rst
docs/phydmslib.constants.rst
docs/phydmslib.file_io.rst
docs/phydmslib.models.rst
docs/phydmslib.numutils.rst
docs/phydmslib.parsearguments.rst
docs/phydmslib.rst
docs/phydmslib.simulate.rst
docs/phydmslib.treelikelihood.rst
docs/phydmslib.utils.rst
docs/phydmslib.weblogo.rst
docs/plot_diffprefs_prior.py
docs/weblinks.txt
docs/_static/BloomLogo.jpg
docs/_static/SUMO1_alignment.jpg
docs/_static/custom.css
docs/_static/diffprefs_logoplot.jpg
docs/_static/diffprefs_logoplot.pdf
docs/_static/diffprefs_prior_plot.png
docs/_static/implementation_tree_example.jpg
docs/_static/omegaoverlay_logoplot.jpg
docs/_static/omegaoverlay_logoplot.pdf
docs/_static/prefs_logoplot.jpg
docs/_static/prefs_logoplot.pdf
phydms.egg-info/PKG-INFO
phydms.egg-info/SOURCES.txt
phydms.egg-info/dependency_links.txt
phydms.egg-info/requires.txt
phydms.egg-info/top_level.txt
phydmslib/__init__.py
phydmslib/_metadata.py
phydmslib/_weblogo_template.eps
phydmslib/constants.py
phydmslib/file_io.py
phydmslib/models.py
phydmslib/numutils.c
phydmslib/numutils.pyx
phydmslib/parsearguments.py
phydmslib/simulate.py
phydmslib/treelikelihood.py
phydmslib/utils.py
phydmslib/weblogo.py
scripts/phydms
scripts/phydms_comprehensive
scripts/phydms_divpressure
scripts/phydms_logoplot
scripts/phydms_prepalignment
tests/README.rst
tests/profile_phydms.py
tests/run_tests.py
tests/run_time_test.err
tests/run_time_test.out
tests/run_time_test.py
tests/test_YNGKPM0.py
tests/test_alignmentSimulation.py
tests/test_alignmentSimulationRandomSeed.py
tests/test_alignmentSimulation_divpressure.py
tests/test_branchScale.py
tests/test_brlenderivatives.py
tests/test_brlenoptimize.py
tests/test_diffprefsbysite.py
tests/test_doctests.py
