Metadata-Version: 1.1
Name: phydms
Version: 2.4.1
Summary: Phylogenetic analyses informed by deep mutational scanning data.
Home-page: http://jbloomlab.github.io/phydms
Author: the Bloom lab (see https://github.com/jbloomlab/phydms/contributors)
Author-email: jbloom@fredhutch.org
License: GPLv3
Download-URL: https://github.com/jbloomlab/phydms/tarball/2.4.1
Platform: UNKNOWN
